MANIFEST.in
setup.cfg
setup.py
bin/salt_state_graph
salt_state_graph/__init__.py
salt_state_graph/test_graph.py
salt_state_graph.egg-info/PKG-INFO
salt_state_graph.egg-info/SOURCES.txt
salt_state_graph.egg-info/dependency_links.txt
salt_state_graph.egg-info/requires.txt
salt_state_graph.egg-info/top_level.txt
salt_state_graph/testdata/postgresql.dot
salt_state_graph/testdata/postgresql.json