Metadata-Version: 1.0
Name: salt-state-graph
Version: 0.0.1
Summary: a tool to represent salt states and their dependencies as an acyclic graph
Home-page: https://github.com/ceralena/salt-state-graph
Author: Cera Davies
Author-email: ceralena.davies@learnosity.com
License: UNKNOWN
Platform: UNKNOWN
